tvbutler
