Metadata-Version: 1.0
Name: tvbutler
Version: 0.1a2
Summary: tvbutler reads RSS feeds from http://tvtorrents.com and downloads torrents of new episodes for you in your preferred quality
Home-page: https://github.com/tomster/tvbutler
Author: Tom Lazar
Author-email: tom@tomster.org
License: BSD
Keywords: rss bittorrent tv
Platform: UNKNOWN
Classifier: Environment :: Console
Classifier: Development Status :: 3 - Alpha
Classifier: License :: OSI Approved :: BSD License
Classifier: Programming Language :: Python :: 2.5
Classifier: Programming Language :: Python :: 2.6
Classifier: Topic :: Multimedia :: Video
Classifier: Topic :: Communications :: File Sharing
